{"_type":"export","__export_format":4,"__export_date":"2023-11-20T02:34:43.578Z","__export_source":"insomnia.desktop.app:v2023.4.0","resources":[{"_id":"req_5e63c37755164033a171d07e0b1b6fa6","parentId":"fld_8b1082826ff34cbd9479a394ec8d375c","modified":1700446230333,"created":1700442475126,"url":"http://localhost:3000/subjects/students/1","name":"enrollSubject","description":"","method":"POST","body":{"mimeType":"application/json","text":"{\n\t\"subjectId\": 2\n}"},"parameters":[],"headers":[{"name":"Content-Type","value":"application/json"}],"authentication":{},"metaSortKey":-1700442061654.917,"isPrivate":false,"settingStoreCookies":true,"settingSendCookies":true,"settingDisableRenderRequestBody":false,"settingEncodeUrl":true,"settingRebuildPath":true,"settingFollowRedirects":"global","_type":"request"},{"_id":"fld_8b1082826ff34cbd9479a394ec8d375c","parentId":"wrk_7eb4ed9c46f844809cc8e63f6668b484","modified":1700442061715,"created":1700442061715,"name":"Subjects","description":"","environment":{},"environmentPropertyOrder":null,"metaSortKey":-1700442061715,"_type":"request_group"},{"_id":"wrk_7eb4ed9c46f844809cc8e63f6668b484","parentId":null,"modified":1700441958829,"created":1700441958829,"name":"mini projeto","description":"","scope":"collection","_type":"workspace"},{"_id":"req_0f83f4859a8547c4babd3fdbb46de156","parentId":"fld_8b1082826ff34cbd9479a394ec8d375c","modified":1700446235378,"created":1700443953001,"url":"http://localhost:3000/subjects/students/1/cancel","name":"cancelSubject","description":"","method":"POST","body":{"mimeType":"application/json","text":"{\n\t\"subjectId\": 2\n}"},"parameters":[],"headers":[{"name":"Content-Type","value":"application/json"}],"authentication":{},"metaSortKey":-1700442061629.917,"isPrivate":false,"settingStoreCookies":true,"settingSendCookies":true,"settingDisableRenderRequestBody":false,"settingEncodeUrl":true,"settingRebuildPath":true,"settingFollowRedirects":"global","_type":"request"},{"_id":"req_abf06740828f4127ad6e4952bc3cf8f6","parentId":"fld_8b1082826ff34cbd9479a394ec8d375c","modified":1700444512283,"created":1700442063099,"url":"http://localhost:3000/subjects/student/1","name":"GetByStudentId","description":"","method":"GET","body":{"mimeType":"application/json","text":""},"parameters":[],"headers":[{"name":"Content-Type","value":"application/json"}],"authentication":{},"metaSortKey":-1700442061604.917,"isPrivate":false,"settingStoreCookies":true,"settingSendCookies":true,"settingDisableRenderRequestBody":false,"settingEncodeUrl":true,"settingRebuildPath":true,"settingFollowRedirects":"global","_type":"request"},{"_id":"req_eaa46c2e2f3048a0a4d50fda87d650eb","parentId":"fld_70fe68a93a3a42378a4b5e2ae6fe5d9a","modified":1700446252288,"created":1700444829479,"url":"http://localhost:3000/libraries/students/2","name":"reserveBook","description":"","method":"POST","body":{"mimeType":"application/json","text":"{\n\t\"bookId\": 2\n}"},"parameters":[],"headers":[{"name":"Content-Type","value":"application/json"}],"authentication":{},"metaSortKey":-1700442061654.917,"isPrivate":false,"settingStoreCookies":true,"settingSendCookies":true,"settingDisableRenderRequestBody":false,"settingEncodeUrl":true,"settingRebuildPath":true,"settingFollowRedirects":"global","_type":"request"},{"_id":"fld_70fe68a93a3a42378a4b5e2ae6fe5d9a","parentId":"wrk_7eb4ed9c46f844809cc8e63f6668b484","modified":1700444829475,"created":1700444829475,"name":"Libraries","description":"","environment":{},"environmentPropertyOrder":null,"metaSortKey":-1700442030952.5,"_type":"request_group"},{"_id":"req_8e1a2d420a3b425d98a3f33d516d39d4","parentId":"fld_70fe68a93a3a42378a4b5e2ae6fe5d9a","modified":1700446266603,"created":1700444829481,"url":"http://localhost:3000/libraries/students/2/cancel","name":"cancelBook","description":"","method":"POST","body":{"mimeType":"application/json","text":"{\n\t\"bookId\": 2\n}"},"parameters":[],"headers":[{"name":"Content-Type","value":"application/json"}],"authentication":{},"metaSortKey":-1700442061629.917,"isPrivate":false,"settingStoreCookies":true,"settingSendCookies":true,"settingDisableRenderRequestBody":false,"settingEncodeUrl":true,"settingRebuildPath":true,"settingFollowRedirects":"global","_type":"request"},{"_id":"req_2785523f2f2c4ffabae7d040088e1a3b","parentId":"fld_70fe68a93a3a42378a4b5e2ae6fe5d9a","modified":1700444924688,"created":1700444829477,"url":"http://localhost:3000/libraries/student/2","name":"GetByStudentId","description":"","method":"GET","body":{"mimeType":"application/json","text":""},"parameters":[],"headers":[{"name":"Content-Type","value":"application/json"}],"authentication":{},"metaSortKey":-1700442061604.917,"isPrivate":false,"settingStoreCookies":true,"settingSendCookies":true,"settingDisableRenderRequestBody":false,"settingEncodeUrl":true,"settingRebuildPath":true,"settingFollowRedirects":"global","_type":"request"},{"_id":"req_2b4828e3781040a38fb156f0e7820097","parentId":"fld_90798025fda04c069191a5166add30b3","modified":1700442041604,"created":1700442018561,"url":"http://localhost:3000/students","name":"GetAll","description":"","method":"GET","body":{},"parameters":[],"headers":[],"authentication":{},"metaSortKey":-1700442018561,"isPrivate":false,"settingStoreCookies":true,"settingSendCookies":true,"settingDisableRenderRequestBody":false,"settingEncodeUrl":true,"settingRebuildPath":true,"settingFollowRedirects":"global","_type":"request"},{"_id":"fld_90798025fda04c069191a5166add30b3","parentId":"wrk_7eb4ed9c46f844809cc8e63f6668b484","modified":1700442000190,"created":1700442000190,"name":"Students","description":"","environment":{},"environmentPropertyOrder":null,"metaSortKey":-1700442000190,"_type":"request_group"},{"_id":"req_fffe46d0ed634e8c8aa2552b880220cc","parentId":"fld_90798025fda04c069191a5166add30b3","modified":1700442054727,"created":1700442052846,"url":"http://localhost:3000/students/1","name":"GetById","description":"","method":"GET","body":{},"parameters":[],"headers":[],"authentication":{},"metaSortKey":-1695897173632.5,"isPrivate":false,"settingStoreCookies":true,"settingSendCookies":true,"settingDisableRenderRequestBody":false,"settingEncodeUrl":true,"settingRebuildPath":true,"settingFollowRedirects":"global","_type":"request"},{"_id":"env_c43388d2677c5d1f01c65f9290001ac5e8a31fb8","parentId":"wrk_7eb4ed9c46f844809cc8e63f6668b484","modified":1700441958831,"created":1700441958831,"name":"Base Environment","data":{},"dataPropertyOrder":null,"color":null,"isPrivate":false,"metaSortKey":1700441958831,"_type":"environment"},{"_id":"jar_c43388d2677c5d1f01c65f9290001ac5e8a31fb8","parentId":"wrk_7eb4ed9c46f844809cc8e63f6668b484","modified":1700441958832,"created":1700441958832,"name":"Default Jar","cookies":[],"_type":"cookie_jar"}]}